odoo/addons/partner_disable_gravatar/README.rst
odoo/addons/partner_disable_gravatar/__init__.py
odoo/addons/partner_disable_gravatar/__manifest__.py
odoo/addons/partner_disable_gravatar/i18n/es.po
odoo/addons/partner_disable_gravatar/i18n/it.po
odoo/addons/partner_disable_gravatar/i18n/partner_disable_gravatar.pot
odoo/addons/partner_disable_gravatar/models/__init__.py
odoo/addons/partner_disable_gravatar/models/res_partner.py
odoo/addons/partner_disable_gravatar/readme/CONFIGURE.rst
odoo/addons/partner_disable_gravatar/readme/CONTRIBUTORS.rst
odoo/addons/partner_disable_gravatar/readme/DESCRIPTION.rst
odoo/addons/partner_disable_gravatar/static/description/icon.png
odoo/addons/partner_disable_gravatar/static/description/index.html
odoo/addons/partner_disable_gravatar/tests/__init__.py
odoo/addons/partner_disable_gravatar/tests/test_partner_disable_gravatar.py
odoo14_addon_partner_disable_gravatar-14.0.1.0.1.dev8.dist-info/METADATA
odoo14_addon_partner_disable_gravatar-14.0.1.0.1.dev8.dist-info/WHEEL
odoo14_addon_partner_disable_gravatar-14.0.1.0.1.dev8.dist-info/top_level.txt
odoo14_addon_partner_disable_gravatar-14.0.1.0.1.dev8.dist-info/RECORD
